{"responses":{"200":{"description":"OK","content":{"application/json":{"schema":{"type":"object","properties":{"year":{"type":"integer","description":"Agreement year."},"target":{"type":"string","description":"Target company name."},"acquirer":{"type":"string","description":"Acquirer company name."},"filing_date":{"type":"string","description":"SEC filing date, when available.","nullable":true},"prob_filing":{"type":"number","description":"Model confidence score for filing linkage.","nullable":true},"filing_company_name":{"type":"string","description":"Filing entity name in SEC metadata.","nullable":true},"filing_company_cik":{"type":"string","description":"Filing entity CIK in SEC metadata.","nullable":true},"form_type":{"type":"string","description":"SEC form type.","nullable":true},"exhibit_type":{"type":"string","description":"SEC exhibit type.","nullable":true},"transaction_price_total":{"type":"number","description":"Total transaction value when available.","nullable":true},"transaction_price_stock":{"type":"number","description":"Stock portion of transaction consideration.","nullable":true},"transaction_price_cash":{"type":"number","description":"Cash portion of transaction consideration.","nullable":true},"transaction_price_assets":{"type":"number","description":"Asset portion of transaction consideration.","nullable":true},"transaction_consideration":{"type":"string","description":"High-level consideration type classification.","nullable":true},"target_type":{"type":"string","description":"Target company type.","nullable":true},"acquirer_type":{"type":"string","description":"Acquirer company type.","nullable":true},"target_industry":{"type":"string","description":"Target industry classification.","nullable":true},"acquirer_industry":{"type":"string","description":"Acquirer industry classification.","nullable":true},"announce_date":{"type":"string","description":"Public deal announcement date.","nullable":true},"close_date":{"type":"string","description":"Deal close date, when available.","nullable":true},"deal_status":{"type":"string","description":"Current status of the deal.","nullable":true},"attitude":{"type":"string","description":"Deal attitude classification.","nullable":true},"deal_type":{"type":"string","description":"Deal type classification.","nullable":true},"purpose":{"type":"string","description":"Deal purpose classification.","nullable":true},"target_pe":{"type":"boolean","description":"Whether target is private-equity backed.","nullable":true},"acquirer_pe":{"type":"boolean","description":"Whether acquirer is private-equity backed.","nullable":true},"url":{"type":"string","description":"Source filing URL."},"xml":{"type":"string","description":"Agreement XML content (may be redacted for anonymous access)."},"is_redacted":{"type":"boolean","description":"Present and true when XML has been redacted for access control."}},"title":"AgreementResponse"}}}},"422":{"description":"Unprocessable Entity","content":{"application/json":{"schema":{"type":"object","properties":{"code":{"type":"integer","description":"Error code"},"status":{"type":"string","description":"Error name"},"message":{"type":"string","description":"Error message"},"errors":{"type":"object","description":"Errors","additionalProperties":{}}},"title":"Error"}}}},"default":{"description":"Default error response","content":{"application/json":{"schema":{"type":"object","properties":{"code":{"type":"integer","description":"Error code"},"status":{"type":"string","description":"Error name"},"message":{"type":"string","description":"Error message"},"errors":{"type":"object","description":"Errors","additionalProperties":{}}},"title":"Error"}}}}}}